{
	"@type":"Process",
	"Name":"ProcessAnalysisFX - Post Wrapper",
	"HasSecurityAccess":false,
	"Code@Code.link":"ProcessAnalysisFX - Post Wrapper.ti",
	"UIData":"CubeAction=1511\fDataAction=1503\fCubeLogChanges=0\f",
	"DataSource":
	{
		"Type":"None"
	},
	"Parameters":
	[
		{
			"Name":"pVersion",
			"Prompt":"Version to Convert",
			"Value":"Actuals",
			"Type":"String"
		},
		{
			"Name":"pYear",
			"Prompt":"Year to Convert",
			"Value":"2018",
			"Type":"String"
		},
		{
			"Name":"pCurrency",
			"Prompt":"Yes/No Run Currency Conversion",
			"Value":"No",
			"Type":"String"
		},
		{
			"Name":"pRestatement",
			"Prompt":"Yes/No Run Restatement",
			"Value":"No",
			"Type":"String"
		},
		{
			"Name":"pVariation",
			"Prompt":"Yes/No Run Currency Elim Var",
			"Value":"No",
			"Type":"String"
		},
		{
			"Name":"pCurrencyTo",
			"Prompt":"Currency to Convert To",
			"Value":"AUD",
			"Type":"String"
		},
		{
			"Name":"pPost",
			"Prompt":"Post for Currency Pull",
			"Value":"All Posts",
			"Type":"String"
		},
		{
			"Name":"pFX",
			"Prompt":"Yes/No Run FX Update",
			"Value":"No",
			"Type":"String"
		},
		{
			"Name":"pYearFrom",
			"Prompt":"Year to copy from",
			"Value":"2018",
			"Type":"String"
		},
		{
			"Name":"pMonStart",
			"Prompt":"Start Month",
			"Value":"Jul",
			"Type":"String"
		},
		{
			"Name":"pMonEnd",
			"Prompt":"End Month",
			"Value":"Jun",
			"Type":"String"
		},
		{
			"Name":"pVersionFrom",
			"Prompt":"Version to copy from",
			"Value":"Budget",
			"Type":"String"
		},
		{
			"Name":"pCurrencyType",
			"Prompt":"Currency Type From",
			"Value":"Opex",
			"Type":"String"
		},
		{
			"Name":"pCurrencyTypeTo",
			"Prompt":"Currency Type To",
			"Value":"Opex",
			"Type":"String"
		}
	],
	"Variables":[]
}